{
  "player_build_data": [
    {
      "type": "playerBuildTimingData",
      "msg": {
        "build_event_id": "75eb82fae74754c5691af7a8a5f57b4c",
        "build_player": 20630,
        "preprocess_player": 4498,
        "produce_player_script_assemblies": 3128,
        "build_scripts_dlls": 12,
        "postprocess_built_player": 6146,
        "node_summary_table": [
          {
            "name": "Csc",
            "duration": 2003
          }
        ]
      },
      "version": 1
    }
  ]
}